Workbook

Sheet Sheet1
A1: Username | B1: Name | C1: Direct Permission Sets | D1: User License | E1: Profile | F1: Role | G1: Manager | H1: Title | I1: Company | J1: Direct Permission Set Count | L1: Permission Set Group Count | N1: Direct Permission Set Source
A2: areid@probomedical.com | B2: Aaliyah Reid | C2: "Super User"; Access to purchasing fields but not creating opps; Add Asset Page; Add Product Page; All Account Fields; Change Account Owner; Create Item Receipts; Create new assets; Create Purchasing Opps; Creating Price Books; Edit Loaner Fields; Endoscopy Test/Repair Permission Set; Executive Power; Full access to evaluations; Full access to work orders; IR PR PO Bill Permissions; Loaner Assets Object; Loaner Object; PandaDoc Access; Pandadoc Object Permissions; Print Shipping Checklist Button; Product Test Page Tab Visibility; Purchasing Fields; Purchasing Opportunity Item Receipts; Sales Opp; Sales Opportunity Access; Ship to Account Opp; Shipping Account Number - Opps; Shipping/Receiving; Trisonics User; UK Admin Permission Set; Uncheck reserve box; Work Order Line Items; Work Order Shipping - Sales Ops; Zenkraft - Full Access | D2: Salesforce | E2: Sales Manager | H2: Customer Service Temp | I2: Probo Medical | J2: =COUNTIF('Direct Permission Sets'!$B$2:$B$7222,A2) | N2: Added from ProboMedical SOQL export. Rows: 7221. Assignment Source = Direct Permission Set, excluding profile-owned permission sets and permission set group assignments.
A3: aposton@probomedical.com | B3: Aaron Poston | C3: Add Asset Page; Add Product Page; All Account Fields; All RMA Fields; Asset and Product Analytics Modify All; Change Record Type RMA; Change RMA action; Cold Storage - Warehouse Reps; Create and Edit Purchasing Returns; Create Item Receipts; Create new assets; Create Products; Creating New Products; Delete RMAs; Edit Serial# on Assets; Handle Assets; Intercompany Transfer Opportunities; Intercompany Transfers Object; IR PR PO Bill Permissions; Loaner Assets Object; Loaner Object; PandaDoc Access; Pandadoc Object Permissions; Parts Operations; Parts Product Name Field; Print Shipping Checklist Button; Product Repair Access; Product Test; Reports and Dashboards; RMA Action (without approval permissions); RMA on Evaluations; Shipping Account Number - Opps; Shipping Cost; Shipping Team; Shipping/Receiving; Sold; Work Order Line Items; Work Order Shipping - Sales Ops; Zenkraft - Admin; Zenkraft - Full Access; Zenkraft - Read Only; Zenkraft - Read-Only User; Zenkraft - Standard User | D3: Salesforce | E3: QC Manager | F3: Ops Manager | I3: AlphaSource Group | J3: =COUNTIF('Direct Permission Sets'!$B$2:$B$7222,A3)
A4: adam.brzostowski@probomedical.co.uk | B4: Adam Brzostowski | C4: Field Service Mobile License; Field Service Resource License; Field Service Resource Permissions; Flow User; Lead Access - FSL Tech (Can Create Leads); Product Analytics and Asset Permissions | D4: Salesforce | E4: Engineer - UK | F4: Engineer - UK | G4: Adam Ward | H4: Senior Engineer | J4: =COUNTIF('Direct Permission Sets'!$B$2:$B$7222,A4)
A5: amorris1@probomedical.com | B5: Adam Morris | C5: Field Service Mobile License; Field Service Resource License; Field Service Resource Permissions; Flow User; FSL Create Lead Perms; FSR Attached; US FSL V1 Perm | D5: Salesforce | E5: FSL US | G5: Hobie Sears | J5: =COUNTIF('Direct Permission Sets'!$B$2:$B$7222,A5)
A6: amorris@probomedical.com | B6: Adam Morris | D6: Customer Community Plus | E6: FSE Portal | F6: Probo Medical - Portal Customer User | H6: FSE | J6: =COUNTIF('Direct Permission Sets'!$B$2:$B$7222,A6)
A7: awalter@probomedical.com | B7: Adam Walter | C7: Add Asset Page; Add Product Page; All Record Types; Create external repairs; Edit cost fields; Full access to evaluations; Invoice Permissions; Loaner Assets Object; Loaner Object; Reports and Dashboards; RMA action and approval permissions; Service Contract Management; Switch to Lightning; SWO/HWO; Two Factor Authentication Required; View Customer Satisfaction Surveys; Warranty claims and products; Zenkraft - Admin | D7: Salesforce | E7: System Administrator Custom | F7: Business Development Manager | I7: Probo Medical, Inc. | J7: =COUNTIF('Direct Permission Sets'!$B$2:$B$7222,A7)
A8: awalter@guest.probomedical.com | B8: Adam Walter | D8: Customer Community Plus | E8: Oncura Portal | F8: Oncura Partners Customer Manager | I8: Probo Medical, Inc. | J8: =COUNTIF('Direct Permission Sets'!$B$2:$B$7222,A8)
A9: adam.ward@probomedical.co.uk | B9: Adam Ward | C9: Add Asset Page; Add Product Page; Create Products; Creating New Products; Edit CLI Peripheral, Service Network, and Service Hardware and Software Fields; Edit Opportunities; Edit Product Status; Field Service Dispatcher License; Field Service Dispatcher Permissions; Field Service Mobile License; Field Service Resource License; Field Service Resource Permissions; Flow User; Handle Assets; Lead Access - FSL Tech (Can Create Leads); PandaDoc Access; Pandadoc Object Permissions; Product Analytics and Asset Permissions; Sales Opportunity Access; Service Contract Management; SWO/HWO | D9: Salesforce | E9: Commercial Manager - UK | F9: Manager - UK | G9: Tom Meredith | J9: =COUNTIF('Direct Permission Sets'!$B$2:$B$7222,A9)
A10: azanga@probomedical.com | B10: Aidan Zanga | C10: Access to harvest work orders; Add Asset Page; Add Product Page; All Record Types; AP Page - Cost; Asset Cost; Check repair information; Create new assets; Edit Ratings Object; Edit Ratings/Notes on Asset Page; Edit review status; Edit Serial# on Assets; Export Reports; Functional Rating for Parts; Loaner Assets Object; Loaner Object; Move Location Enabled; Part Tests and Repairs; Parts Operations; Parts Record Type; Product Test; Product Test Edit; Purchase Approval Checkbox; Reports and Dashboards; Systems Test; Two Factor Authentication Required | D10: Salesforce | E10: QC Manager | H10: Component Repair Engineer | I10: Probo Medical, Inc. | J10: =COUNTIF('Direct Permission Sets'!$B$2:$B$7222,A10)
A11: amirko@proborestoration.com | B11: Alex Mirko | C11: Flow User | D11: Salesforce | E11: Mechanical Services | J11: =COUNTIF('Direct Permission Sets'!$B$2:$B$7222,A11)
A12: apogrebinsky@probomedical.com | B12: Alex Pogrebinsky | C12: Access to harvest work orders; Add Asset Page; Add Product Page; All Record Types; All RMA Fields; Asset and Product Analytics Modify All; Asset2- Review Status; Create new assets; Creating New Products; Creating Price Books; Edit Ratings/Notes on Asset Page; PandaDoc Access; Pandadoc Object Permissions; Parts Operations; Parts Record Type; Print Shipping Checklist Button; Product Test; Repairable Fields; Shipping Team; Shipping/Receiving | D12: Salesforce | E12: QC Manager | F12: Ops Tech | I12: AlphaSource Group | J12: =COUNTIF('Direct Permission Sets'!$B$2:$B$7222,A12)
A13: adamato@probomedical.com | B13: Alexus D'Amato | C13: Add Asset Page; Add Product Page; Cold Storage - Invoicing; Cold Storage - Warehouse Reps; Location Unlocked; Move Location Enabled; PandaDoc Access; Pandadoc Object Permissions; Training Class/Class Attendance Access | D13: Salesforce | E13: Sales Manager | H13: Project Coordinator | I13: AlphaSource Group | J13: =COUNTIF('Direct Permission Sets'!$B$2:$B$7222,A13)
A14: alfie.john@probomedical.co.uk | B14: Alfie John | C14: Chargent User (Base); Chargent User (Orders); Flow User; Invoice Permissions; Manage Intacct Synced Records; PandaDoc Access; Pandadoc Object Permissions; Physical Location on Invoice Object; Product Analytics and Asset Permissions | D14: Salesforce | E14: Commercial Finance - UK | H14: European Accounts Payable Assistant | I14: Probo Medical, Ltd. | J14: =COUNTIF('Direct Permission Sets'!$B$2:$B$7222,A14)
A15: aekizian@probomedical.com | B15: Aline Ekizian | C15: Add Asset Page; Add Product Page; PandaDoc Access; Pandadoc Object Permissions | D15: Salesforce | E15: Sales Manager | F15: Sales Manager | G15: Dur Thomason | H15: Director, Enterprise Sales - West | I15: Probo Medical | J15: =COUNTIF('Direct Permission Sets'!$B$2:$B$7222,A15)
A16: alison.williams@probomedical.co.uk | B16: Alison Williams | C16: Access to Product & Repair Pricing; Access to purchasing fields but not creating opps; Add Asset Page; Add Product Page; All RMA Fields; Create Item Receipts; Create new assets; Create Purchasing Opps; Field Service Dispatcher License; Field Service Dispatcher Permissions; Flow User; Pandadoc Object Permissions; Product Analytics and Asset Permissions; Purchasing Fields | D16: Salesforce | E16: Commercial Sales - UK | F16: Manager - UK | G16: Tom Meredith | H16: Large Equipment Service Coordinator | I16: Probo Medical, Ltd. | J16: =COUNTIF('Direct Permission Sets'!$B$2:$B$7222,A16)
A17: alpha_source@ultrasoundrepair.force.com | B17: Alpha Source Site Guest User | D17: Guest User License | E17: Alpha Source Profile | J17: =COUNTIF('Direct Permission Sets'!$B$2:$B$7222,A17)
A18: ahaley@probomedical.com | B18: Alyssa Haley | C18: Add Asset Page; Add Product Page; PandaDoc Access; Pandadoc Object Permissions | D18: Salesforce | E18: Sales User | F18: Sales Rep | H18: Veterinary Ultrasound Sales Manager | I18: Probo Medical, Inc. | J18: =COUNTIF('Direct Permission Sets'!$B$2:$B$7222,A18)
A19: avondrach@probomedical.com | B19: Alyssa VonDrach | C19: Add Product Page; All Record Types; All RMA Fields; Asset and Product Analytics Modify All; Asset2- Review Status; Big Iron Opportunity Type; Change Opportunity Owner; Create new assets; Create Purchasing Opps; Creating New Products; Credit Memo- View Access; Delete RMAs; Deleting/Merging Accounts; Field Service Dispatcher Permissions; Field Service Mobile License; Field Service Resource License; Intercompany Transfer Opportunities; Intercompany Transfers Object; Invoice Permissions; IR PR PO Bill Permissions; Loaner Assets Object; Loaner Object; Loaner Turned Exchange; Manage Assets; Manage Billing Address on Intacct Synced Account; Opportunity - Delete Records; PandaDoc Access; Pandadoc Object Permissions; Product Dealer Pricing; Purchasing Fields; Record Types- Harrisburg Sales; Reports and Dashboards; Sales Opportunity Access; Service Contract Management; Shipping Cost; Shipping/Receiving; Switch to Lightning; SWO/HWO; Total Cost of Assets; Trisonics User; Vendor Sourcing; Vendor Sourcing Full Access; Work Order Shipping - Sales Ops; Zenkraft - Read Only; Zenkraft - Standard User | D19: Salesforce | E19: Sales User | F19: Sales Rep | I19: Probo Medical, Inc. | J19: =COUNTIF('Direct Permission Sets'!$B$2:$B$7222,A19)
A20: aboyko@probomedical.com | B20: Amanda Boyko | C20: Add Asset Page; Add Product Page; PandaDoc Access; Pandadoc Object Permissions | D20: Salesforce | E20: Sales User | H20: Sales | I20: Probo Medical, Inc | J20: =COUNTIF('Direct Permission Sets'!$B$2:$B$7222,A20)
A21: ahironimus@probomedical.com | B21: Amber Hironimus | C21: Add Asset Page; Add Product Page; All Record Types; All RMA Fields; ApprovalForm access; Asset and Product Analytics Modify All; Asset Cost; Asset2- Review Status; Big Iron Opportunity Type; Certain Asset Fields; Change Opportunity Owner; Change Record Type RMA; Create new assets; Create Warranty Ops; Creating New Products; Credit Memo- View Access; Delete RMAs; Deleting/Merging Accounts; Edit cost fields; Edit review status; Edit Serial# on Assets; Field Service Dispatcher Permissions; Field Service Mobile License; Field Service Resource License; Field Service Resource Permissions; FieldServiceMobileStandardPermSetUS; Flow User; Intercompany Transfer Opportunities; Invoice Permissions; IR PR PO Bill Permissions; Loaner Assets Object; Loaner Object; Loaner Turned Exchange; Manage Assets; Manage Billing Address on Intacct Synced Account; Move Location Enabled; Non-Conforming Record Access; Opportunity - Delete Records; PandaDoc Access; Pandadoc Object Permissions; Product Dealer Pricing; Purchasing Fields; Record Types- Harrisburg Sales; Reports and Dashboards; RMA on Evaluations; Sales Opportunity Access; Service Contract Management; Shipping Cost; Switch to Lightning; SWO/HWO; Trisonics User; Two Factor Authentication Required; Uncheck reserve box; US FSL V1 Perm; Vendor Sourcing; Vendor Sourcing Full Access; Work Order Shipping - Sales Ops; Zenkraft - Read Only; Zenkraft - Standard User | D21: Salesforce | E21: Sales Manager | I21: Probo Medical, Inc. | J21: =COUNTIF('Direct Permission Sets'!$B$2:$B$7222,A21)
A22: amy.sharp@probomedical.co.uk | B22: Amy Sharp | C22: Add Product Page; Change Invoice Number on Opp; Chargent User (Base); Chargent User (Orders); Invoice Permissions; Manage Billing Address on Intacct Synced Account; Manage Intacct Synced Records; Manage Payment Terms, Credit Limit on Intacct Synced Account; PandaDoc Access; Pandadoc Object Permissions; Physical Location on Invoice Object; Product Analytics and Asset Permissions | D22: Salesforce | E22: Commercial Finance - UK | G22: Tina Betts | H22: European Accounting Coordinator | I22: Probo Medical, Ltd. | J22: =COUNTIF('Direct Permission Sets'!$B$2:$B$7222,A22)
A23: ahoward@probomedical.com | B23: Ana Howard | C23: Add Product Page; All Record Types; Asset and Product Analytics Modify All; Loaner Assets Object; Loaner Object; Modify All - Assets; SWO/HWO; Two Factor Authentication Required | D23: Salesforce | E23: Repair Tech | I23: Probo Medical, Inc. | J23: =COUNTIF('Direct Permission Sets'!$B$2:$B$7222,A23)
A24: aserrano@probomedical.com | B24: Ana Serrano | C24: Add Asset Page; Add Product Page; All Record Types; AP Page - Cost; Asset Cost; Big Iron Opportunity Type; Chargent Payment Console; Chargent Payment Request; Chargent Terminal Unlinked Payments; Chargent Terminal User; Chargent User (Base); Chargent User (Orders); IR PR PO Bill Permissions; Loaner Assets Object; Manage Intacct Synced Records; Pandadoc Object Permissions; Reports and Dashboards; Return from Sale RMA; SWO/HWO | D24: Salesforce | E24: Accounting | I24: Probo Medical, Inc. | J24: =COUNTIF('Direct Permission Sets'!$B$2:$B$7222,A24)
A25: aisley@probomedical.com | B25: Andrea Isley | C25: Add Asset Page; Add Product Page; Asset Reserved Checkbox; Lead Owner Change; Marketing - Lead Assignment; PandaDoc Access; Pandadoc Object Permissions | D25: Salesforce | E25: Sales Manager | J25: =COUNTIF('Direct Permission Sets'!$B$2:$B$7222,A25)
A26: andreea.dura@probomedical.co.uk | B26: Andreea Dura | C26: Change Account Owner; Field Service Guest User Permissions; PandaDoc Access; Pandadoc Object Permissions; Product Analytics and Asset Permissions | D26: Salesforce | E26: Commercial Sales - UK | F26: Manager - UK | G26: Lee Moger | H26: Account Manager | I26: Probo Medical Ltd. | J26: =COUNTIF('Direct Permission Sets'!$B$2:$B$7222,A26)
A27: acarvajal@probomedical.com | B27: Andres Carvajal | C27: Add Asset Page; Add Product Page; All Record Types; Check repair information; Edit Public Reports; Export Reports; Functional Rating for Parts; Loaner Assets Object; Loaner Object; Location Unlocked; Part Tests and Repairs; Parts Operations; Parts Record Type; Product Test; Product Test Edit; Refurb Test & Refurb Part Request Permissions; Repairable Fields; Reports and Dashboards; Systems Test; Two Factor Authentication Required | D27: Salesforce | E27: QC Manager | H27: Diagnostic Engineer | I27: Probo Medical, Inc. | J27: =COUNTIF('Direct Permission Sets'!$B$2:$B$7222,A27)
A28: andrew.fairley@probomedical.co.uk | B28: Andrew Fairley | C28: Field Service Mobile License; Field Service Resource License; Field Service Resource Permissions; Flow User; Lead Access - FSL Tech (Can Create Leads); Product Analytics and Asset Permissions | D28: Salesforce | E28: Engineer - UK | F28: Engineer - UK | G28: Chris Dall-Smith | H28: Senior Engineer | J28: =COUNTIF('Direct Permission Sets'!$B$2:$B$7222,A28)
A29: ajaystewart@probomedical.com | B29: Andrew Jay Stewart | D29: Customer Community Plus | E29: FSE Portal | F29: Probo Medical - Portal Customer User | H29: FSE | I29: Probo Medical, Inc. | J29: =COUNTIF('Direct Permission Sets'!$B$2:$B$7222,A29)
A30: ajaystewart1@probomedical.com | B30: Andrew Jay Stewart | C30: Asset and Product Analytics Modify All; Field Service Mobile License; Field Service Resource License; Field Service Resource Permissions; Flow User; FSL Create Lead Perms; FSR Attached; Lead Access - FSL Tech (Can Create Leads); US FSL V1 Perm | D30: Salesforce | E30: FSL US | G30: Brad Lawson | J30: =COUNTIF('Direct Permission Sets'!$B$2:$B$7222,A30)
A31: andrew.murdoch@probomedical.co.uk | B31: Andrew Murdoch | C31: Field Service Mobile License; Field Service Resource License; Field Service Resource Permissions; Flow User; Lead Access - FSL Tech (Can Create Leads) | D31: Salesforce | E31: Engineer - UK | G31: Chris Dall-Smith | H31: Service Engineer | J31: =COUNTIF('Direct Permission Sets'!$B$2:$B$7222,A31)
A32: andrew.wiltshire@probomedical.co.uk | B32: Andrew Wiltshire | C32: Field Service Mobile License; Field Service Resource License; Field Service Resource Permissions; Flow User; Lead Access - FSL Tech (Can Create Leads); Product Analytics and Asset Permissions | D32: Salesforce | E32: Engineer - UK | G32: Chris Dall-Smith | H32: Senior Engineer | J32: =COUNTIF('Direct Permission Sets'!$B$2:$B$7222,A32)
A33: andy.woodhouse@probomedical.co.uk | B33: Andy Woodhouse | C33: Field Service Mobile License; Field Service Resource License; Field Service Resource Permissions; Flow User; Lead Access - FSL Tech (Can Create Leads); Product Analytics and Asset Permissions | D33: Salesforce | E33: Engineer - UK | F33: Engineer - UK | G33: Chris Dall-Smith | H33: Senior Field Service Engineer | J33: =COUNTIF('Direct Permission Sets'!$B$2:$B$7222,A33)
A34: abates@probomedical.com | B34: Angel Bates | C34: Access to accounting info; Add Asset Page; Add Product Page; All Account Fields; Change Account Owner; Credit Memo Permission Set; Credit Memo- View Access; IR PR PO Bill Permissions; Manage Intacct Synced Records; PandaDoc Access; Pandadoc Object Permissions; Ship to Account Opp; Shipping Account Number - Opps | D34: Salesforce | E34: Accounting + Sales | H34: ASG Credit/Collections | I34: AlphaSource Group | J34: =COUNTIF('Direct Permission Sets'!$B$2:$B$7222,A34)
A35: aficuciello1@probomedical.com | B35: Anthony Ficuciello | C35: Field Service Mobile License; Field Service Resource License; Field Service Resource Permissions; Flow User; FSL Create Lead Perms; FSR Attached; Lead Access - FSL Tech (Can Create Leads); US FSL V1 Perm | D35: Salesforce | E35: FSL US | G35: Brad Lawson | J35: =COUNTIF('Direct Permission Sets'!$B$2:$B$7222,A35)
A36: aficuciello@probomedical.com | B36: Anthony Ficuciello | D36: Customer Community Plus | E36: FSE Portal | F36: Probo Medical - Portal Customer User | H36: FSE | I36: Probo Medical, Inc. | J36: =COUNTIF('Direct Permission Sets'!$B$2:$B$7222,A36)
A37: awhitsit@probomedical.com | B37: Anthony Whitsit | C37: Asset and Product Analytics Modify All; Creating New Products; Loaner Assets Object; Loaner Object; Modify All - Assets; Print Shipping Checklist Button; Product Repair Access; Product Test; Product Test Edit; Shipping Account Number - Opps; Shipping Team; Shipping/Receiving; Unable to further improve - cosmetic; Unable to further improve - functional and cosmetic; Zenkraft - Full Access; Zenkraft - Read Only; Zenkraft - Standard User | D37: Salesforce | E37: Repair Tech Lead | F37: Ops Tech | J37: =COUNTIF('Direct Permission Sets'!$B$2:$B$7222,A37)
A38: areed@probomedical.com | B38: Anton Reed | C38: Add Product Page; All Record Types; Asset and Product Analytics Modify All; Loaner Assets Object; Loaner Object; Modify All - Assets; SWO/HWO; Two Factor Authentication Required; Unable to further improve - cosmetic | D38: Salesforce | E38: Repair Tech | I38: Probo Medical, Inc. | J38: =COUNTIF('Direct Permission Sets'!$B$2:$B$7222,A38)
A39: approval_attachment@probomedical.force.com | B39: Approval Attachment Site Guest User | C39: Approval Form Guest Access | D39: Guest User License | E39: Approval Attachment Profile | I39: Probo Medical, Inc. | J39: =COUNTIF('Direct Permission Sets'!$B$2:$B$7222,A39)
A40: approval_form@probomedical.force.com | B40: Approval Form Site Guest User | C40: Approval Form Guest Access | D40: Guest User License | E40: Approval Form Profile | J40: =COUNTIF('Direct Permission Sets'!$B$2:$B$7222,A40)
A41: alebo@probomedical.com | B41: April Lebo | C41: Access to accounting info; Access to all price fields and product notes on Product Page; Access to Product & Repair Pricing; Add Asset Page; Add Product Page; All Account Fields; All Record Types; All RMA Fields; AP Page - Cost; Approval Form Guest Access; ApprovalForm access; Asset Cost; Asset2- Review Status; Change Account Owner; Change Opportunity Owner; Change Record Type RMA; Change RMA action; Confirmation Number; Create external repairs; Create new assets; Create Products; Create Purchasing Opps; Create Warranty Ops; Create Work Orders; Creating New Products; Creating Price Books; Credit Memo- View Access; Delete RMAs; Delete sourcing requests; Delete Work Order; Deleting/Merging Accounts; e2a Email User; Edit cost fields; Edit Loaner Fields; Edit Product Status; Edit review status; FSR Attached; Full access to evaluations; Full access to work orders; Intercompany Transfer Opportunities; Intercompany Transfers Object; Inventory Life; Invoice Permissions; IR PR PO Bill Permissions; Loaner Assets Object; Loaner Object; Location Unlocked; Manage Assets; Mass Delete OLIs from Opp; PandaDoc Access; Pandadoc Object Permissions; Parts Operations; Parts Record Type; Parts Sales Record Type; Product Dealer Pricing; RMA Action (without approval permissions); RMA on Evaluations; Sales Opportunity Access; Service Contract Management; Shipping/Receiving; Switch to Lightning; SWO/HWO; Trisonics User; Two Factor Authentication Required; UK Admin Permission Set; Vendor information on Asset Page; Vendor Sourcing; Vendor Sourcing Full Access; View Only Access to Evaluations; Warranty claims and products; Work Order Line Items; Work Order Shipping - Sales Ops; Zenkraft - Full Access; Zenkraft - Standard User | D41: Salesforce | E41: Sales Manager | H41: BDR Manager/National Accounts | I41: Probo Medical, Inc. | J41: =COUNTIF('Direct Permission Sets'!$B$2:$B$7222,A41)
A42: arogers@probomedical.com | B42: April Rogers | C42: Access to all price fields and product notes on Product Page; Access to purchasing fields but not creating opps; Add Asset Page; Add Product Page; All RMA Fields; Asset and Product Analytics Modify All; Asset Cost; Cost View; Create Item Receipts; Create new assets; Create Products; Create Purchasing Opps; Creating New Products; Creating Price Books; Edit Dealer Pricing on Parts; Edit Part Status on Ultrasound Part Products; Edit Serial# on Assets; Handle Assets; IR PR PO Bill Permissions; Manage Assets; PandaDoc Access; Pandadoc Object Permissions; Parts Operations; Parts Product Name Field; Parts Record Type; Parts Sales Record Type; Purchasing Fields; Return from Sale RMA; RMA Action (without approval permissions); RMA on Evaluations; Sales Opp; Sales Opportunity Access; Vendor Sourcing; Vendor Sourcing Full Access | D42: Salesforce | E42: Sales Manager | F42: Sales Rep | H42: DI Parts Sales | I42: AlphaSource Group | J42: =COUNTIF('Direct Permission Sets'!$B$2:$B$7222,A42)
A43: agrider@probomedical.com | B43: Arin Grider | C43: Add Product Page; All Record Types; ApprovalForm access; Asset and Product Analytics Modify All; Change Capacitance/Sensitivity; Edit review status; Full access to work orders; Loaner Assets Object; Loaner Object; Modify All - Assets; Purchase Approval Checkbox; Repairable Fields; SWO/HWO; Two Factor Authentication Required; Unable to further improve - functional and cosmetic; Uncheck reserve box; Vendor information on Asset Page | D43: Salesforce | E43: Repair Tech Lead | I43: Probo Medical, Inc. | J43: =COUNTIF('Direct Permission Sets'!$B$2:$B$7222,A43)
A44: arwyn.roberts@probomedical.co.uk | B44: Arwyn Roberts | C44: Field Service Mobile License; Field Service Resource License; Field Service Resource Permissions; Flow User; Lead Access - FSL Tech (Can Create Leads); Product Analytics and Asset Permissions | D44: Salesforce | E44: Engineer - UK | G44: Chris Dall-Smith | H44: Service Engineer | J44: =COUNTIF('Direct Permission Sets'!$B$2:$B$7222,A44)
A45: amadson@probomedical.com | B45: Ashley Madson | C45: Access to accounting info; Access to all price fields and product notes on Product Page; Add Asset Page; Add Product Page; All Record Types; All RMA Fields; AP Page - Cost; ApprovalForm access; Asset and Product Analytics Modify All; Big Iron Opportunity Type; Change Record Type RMA; Change RMA action; Create external repairs; Create new assets; Create Warranty Ops; Creating New Products; Credit Memo- View Access; Delete RMAs; Edit cost fields; Edit Loaner Fields; Edit Product Status; Field Service Dispatcher Permissions; Field Service Mobile License; Field Service Resource License; Field Service Resource Permissions; FieldServiceMobileStandardPermSetUS; Flow User; FSR Attached; Full access to evaluations; Intercompany Transfers Object; Invoice Permissions; IR PR PO Bill Permissions; Loaner Assets Object; Loaner Object; Loaner Turned Exchange; Manage Assets; Manage Billing Address on Intacct Synced Account; Mass Delete OLIs from Opp; Non-Conforming Record Access; PandaDoc Access; Print Shipping Checklist Button; Product Dealer Pricing; Repairable Fields; RMA action and approval permissions; RMA on Evaluations; Sales Opportunity Access; Service Contract Management; Shipping Cost; Shipping/Receiving; Switch to Lightning; SWO/HWO; Two Factor Authentication Required; Uncheck reserve box; US FSL V1 Perm; Vendor Sourcing; Vendor Sourcing Full Access; Warranty claims and products; Work Order Shipping - Sales Ops; Zenkraft - Standard User | D45: Salesforce | E45: System Administrator | H45: Account Manager / Repair Coordinator | I45: Probo Medical, Inc. | J45: =COUNTIF('Direct Permission Sets'!$B$2:$B$7222,A45)
A46: amadson2@probomedical.com | B46: Ashley Madson | D46: Customer Community Plus | E46: FSE Portal | F46: Probo Medical - Portal Customer Manager | J46: =COUNTIF('Direct Permission Sets'!$B$2:$B$7222,A46)
A47: austin.morris@probomedical.com | B47: Austin Morris | D47: Customer Community Plus | E47: FSE Portal | F47: Probo Medical - Portal Customer User | H47: fSE | J47: =COUNTIF('Direct Permission Sets'!$B$2:$B$7222,A47)
A48: austin.morris1@probomedical.com | B48: Austin Morris | C48: Field Service Mobile License; Field Service Resource License; Field Service Resource Permissions; Flow User; FSL Create Lead Perms; FSR Attached; Lead Access - FSL Tech (Can Create Leads); US FSL V1 Perm | D48: Salesforce | E48: FSL US | G48: Hobie Sears | J48: =COUNTIF('Direct Permission Sets'!$B$2:$B$7222,A48)
A49: autoproc@00du0000000lakomak | B49: Automated Process | I49: Lightning Vu Ventures | J49: =COUNTIF('Direct Permission Sets'!$B$2:$B$7222,A49)
A50: b2bmaintegration@00du0000000lakomak.ext | B50: B2BMA Integration | C50: Account Engagement Integration User; All Record Types; Loaner Assets Object; Loaner Object | D50: B2BMA Integration User | E50: B2BMA Integration User | J50: =COUNTIF('Direct Permission Sets'!$B$2:$B$7222,A50)
A51: baljinder.singh@probomedical.co.uk | B51: Baljinder Singh | C51: Create new assets; Create Products; Field Service Mobile License; Field Service Resource License; Field Service Resource Permissions; Flow User; Lead Access - FSL Tech (Can Create Leads); Product Analytics and Asset Permissions; Product Test; SWO/HWO; Systems Test | D51: Salesforce | E51: Engineer - UK | F51: Engineer - UK | G51: Adam Ward | H51: Field Service Engineer | I51: Probo Medical, Ltd. | J51: =COUNTIF('Direct Permission Sets'!$B$2:$B$7222,A51)
A52: balwinder.singh@probomedical.co.uk | B52: Balwinder Singh | C52: Create new assets; Create Products; Field Service Mobile License; Field Service Resource License; Field Service Resource Permissions; Flow User; Lead Access - FSL Tech (Can Create Leads); Product Analytics and Asset Permissions; SWO/HWO; Systems Test | D52: Salesforce | E52: Engineer - UK | G52: Adam Ward | H52: Field Service Engineer | J52: =COUNTIF('Direct Permission Sets'!$B$2:$B$7222,A52)
A53: bdelikat@probomedical.com | B53: Barbara Delikat | C53: Add Asset Page; Add Product Page; Lead Owner Change; Marketing - Lead Assignment; PandaDoc Access; Pandadoc Object Permissions | D53: Salesforce | E53: Sales Manager | J53: =COUNTIF('Direct Permission Sets'!$B$2:$B$7222,A53)
A54: bsheriff@probomedical.com | B54: Barbara Sheriff, RDMS, RVT | C54: Add Product Page; All Record Types; ApprovalForm access; e2a Email User; Loaner Assets Object; Loaner Object; Pandadoc Object Permissions; Scan to Salesforce; Service Contract Management; SWO/HWO; Two Factor Authentication Required | D54: Salesforce | E54: Sales Manager | F54: Sales Manager | H54: Director of Ultrasound Applications | I54: Probo Medical, Inc. | J54: =COUNTIF('Direct Permission Sets'!$B$2:$B$7222,A54)
A55: bstrine@probomedical.com | B55: Baylee Strine | C55: Access to harvest work orders; Add Asset Page; Add Product Page; All RMA Fields; Asset and Product Analytics Modify All; Asset2- Review Status; Create new assets; Creating New Products; Creating Price Books; Edit Ratings Object; Edit Ratings/Notes on Asset Page; PandaDoc Access; Pandadoc Object Permissions; Parts Operations; Parts Record Type; Print Shipping Checklist Button; Product Test; Repairable Fields; Shipping Team; Shipping/Receiving; Uncheck reserve box; Zenkraft - Standard User | D55: Salesforce | E55: QC Manager | F55: Ops Tech | H55: Harvest Specialist | I55: AlphaSource Group | J55: =COUNTIF('Direct Permission Sets'!$B$2:$B$7222,A55)
A56: bkoehler@probomedical.com | B56: Beau Koehler | C56: Access to harvest work orders; Add Asset Page; Add Product Page; All RMA Fields; Asset2- Review Status; Create new assets; Creating New Products; Creating Price Books; Edit Ratings/Notes on Asset Page; Full access to evaluations; PandaDoc Access; Pandadoc Object Permissions; Part Tests and Repairs; Parts Operations; Parts Product Name Field; Parts Record Type; Parts Sales Record Type; Product Test; Repairable Fields; Shipping Team; Shipping/Receiving; Zenkraft - Standard User | D56: Salesforce | E56: QC Manager | F56: Ops Tech | H56: Mechanical Imaging Repair Technician I | I56: Probo Medical US | J56: =COUNTIF('Direct Permission Sets'!$B$2:$B$7222,A56)
A57: bjean@probomedical.com | B57: Bedeline Jean | C57: Intacct Sync Admin; Manage Billing Address on Intacct Synced Account; Manage Intacct Synced Records; Manage Payment Terms, Credit Limit on Intacct Synced Account | D57: Salesforce | E57: Accounting + Sales | H57: Collections Specialist | I57: Probo Medical, US | J57: =COUNTIF('Direct Permission Sets'!$B$2:$B$7222,A57)
A58: ben.rice@probomedical.ca | B58: Ben Rice | C58: Ability to Edit Entity; Access to Product & Repair Pricing; Add Asset Page; Add Product Page; Asset and Product Analytics Modify All; Change Account Owner; Change Asset Ownership; Create new assets; Creating New Products; Invoice Permissions; Location Unlocked; PandaDoc Access; Pandadoc Object Permissions; Product Analytics and Asset Permissions; Sales Opp; Sales Opportunity Access; Scan to Salesforce; Trisonics User | D58: Salesforce | E58: Commercial Manager - UK | H58: SVP Radiology Sales | I58: Probo Medical Ltd | J58: =COUNTIF('Direct Permission Sets'!$B$2:$B$7222,A58)
A59: ben.rice@probomedical.ca.us | B59: Ben Rice US | C59: Ability to Edit Entity; Access to Product & Repair Pricing; Add Asset Page; Add Product Page; Asset and Product Analytics Modify All; Change Account Owner; Change Asset Ownership; Create new assets; Creating New Products; Invoice Permissions; Location Unlocked; PandaDoc Access; Pandadoc Object Permissions; Sales Opportunity Access; Scan to Salesforce; Trisonics User | D59: Salesforce | E59: Commercial Manager - UK | H59: Head of Sales, Big Iron Equipment | I59: Probo Medical Ltd | J59: =COUNTIF('Direct Permission Sets'!$B$2:$B$7222,A59)
A60: bgrider@probomedical.com | B60: Bill Grider | C60: Access to probe repair opps; Access to Product & Repair Pricing; Add Product Page; All Record Types; All RMA Fields; ApprovalForm access; Asset and Product Analytics Modify All; Asset Cost; Asset Reserved Checkbox; Change Capacitance/Sensitivity; Colorful Dashboards; Edit All Dashboards/Reports; Edit sales price field on asset page; Full access to equipment; Full access to evaluations; Full access to work orders; Loaner Assets Object; Loaner Object; Modify All - Assets; Print Shipping Checklist Button; Product Test; Product Test Edit; QC Bump; Repairable Fields; Reports and Dashboards; Reports and Dashboards with View All Data; Shipment Information Fields Permission Set; Shipping Account Number - Opps; Shipping Cost; Shipping Team; Shipping/Receiving; SWO/HWO; Two Factor Authentication Required; View Only Access to Evaluations; Work Order Shipping - Sales Ops; Zenkraft - Standard User | D60: Salesforce | E60: Repair Tech Lead | I60: Probo Medical, Inc. | J60: =COUNTIF('Direct Permission Sets'!$B$2:$B$7222,A60)
A61: bsullivan@probomedical.com | B61: Bill Sullivan | C61: Add Asset Page; Add Product Page; PandaDoc Access; Pandadoc Object Permissions | D61: Salesforce | E61: Sales Manager | G61: Christine Meier | H61: Vice President | I61: Probo Medical, Inc. | J61: =COUNTIF('Direct Permission Sets'!$B$2:$B$7222,A61)
A62: blake.nielsen@probomedical.com | B62: Blake Nielsen | C62: Add Asset Page; Add Product Page; Asset and Product Analytics Modify All; Asset Cost; Cost View; Create new assets; Create Products; Creating New Products; Delete RMAs; Edit cost fields; Edit Part Status on Ultrasound Part Products; Edit Product and Non-Serialized Qty in Stock; Edit Product Status; Edit Ratings Object; Edit Ratings/Notes on Asset Page; Edit review status; Edit Serial# on Assets; Export Reports; Field Service Self Service Permissions; Full access to equipment; Move Location Enabled; PandaDoc Access; Pandadoc Object Permissions; Part Tests and Repairs; Parts Operations; Parts Product Name Field; Parts Record Type; Product Part Edit Pricing; Product Repair Access; Product Test Edit; Purchase Approval Checkbox; Reports and Dashboards; Reports and Dashboards with View All Data; Shipping Cost; Shipping Team; Shipping/Receiving; SWO/HWO; System Work Order - Scrap Asset; Uncheck reserve box; Zenkraft - Admin; Zenkraft - Full Access; Zenkraft - Read Only; Zenkraft - Read-Only User; Zenkraft - Standard User | D62: Salesforce | E62: Sales Manager | G62: Riley Jennings | H62: Director of Operations LOU & SLC | I62: Probo Medical | J62: =COUNTIF('Direct Permission Sets'!$B$2:$B$7222,A62)
A63: block_imaging_portal@00du0000000lakomak.org.force.com | B63: Block Imaging Portal Site Guest User | D63: Guest User License | E63: Block Imaging Portal Profile | J63: =COUNTIF('Direct Permission Sets'!$B$2:$B$7222,A63)
A64: blawson@guest.probomedical.com | B64: Brad Lawson | D64: Customer Community Plus | E64: FSE Portal | F64: Probo Medical - Portal Customer Manager | I64: Probo Medical, Inc. | J64: =COUNTIF('Direct Permission Sets'!$B$2:$B$7222,A64)
A65: blawson@probomedical.com | B65: Brad Lawson | C65: Add Product Page; All Record Types; Field Service Mobile License; Field Service Resource License; Field Service Resource Permissions; FieldServiceMobileStandardPermSetUS; Flow User; FSL Create Lead Perms; FSR Attached; Lead Access - FSL Tech (Can Create Leads); Loaner Assets Object; Loaner Object; Pandadoc Object Permissions; Scan to Salesforce; SWO/HWO; US FSL V1 Perm | D65: Salesforce | E65: Sales User | I65: Probo Medical, Inc. | J65: =COUNTIF('Direct Permission Sets'!$B$2:$B$7222,A65)
A66: bleague@probomedical.com | B66: Brad League | D66: Customer Community Plus | E66: FSE Portal | F66: Probo Medical - Portal Customer User | H66: FSE | I66: Probo Medical, Inc. | J66: =COUNTIF('Direct Permission Sets'!$B$2:$B$7222,A66)
A67: bleague1@probomedical.com | B67: Brad League | C67: Field Service Mobile License; Field Service Resource License; Field Service Resource Permissions; Flow User; FSR Attached; US FSL V1 Perm | D67: Salesforce | E67: FSL US | G67: Hobie Sears | H67: Engineer | J67: =COUNTIF('Direct Permission Sets'!$B$2:$B$7222,A67)
A68: bearly1@probomedical.com | B68: Brandon Early | C68: Field Service Mobile License; Field Service Resource License; Field Service Resource Permissions; Flow User; FSR Attached; US FSL V1 Perm | D68: Salesforce | E68: FSL US | G68: Brad Lawson | H68: Engineer | J68: =COUNTIF('Direct Permission Sets'!$B$2:$B$7222,A68)
A69: brector@probomedical.com | B69: Brandon Rector | C69: Access to probe repair opps; Access to Product & Repair Pricing; Add Product Page; All Record Types; All RMA Fields; AP Page - Cost; ApprovalForm access; Change Record Type RMA; Change RMA action; Check repair information; Delete RMAs; Depot Repair Approvals; External Repair Opportunities; Full access to repairs - non-TEE; Full access to repairs - systems; Full access to repairs - TEE; Loaner Assets Object; Loaner Object; Pandadoc Object Permissions; Part Tests and Repairs; Product Test Page Tab Visibility; Repairable Fields; Return from Sale RMA; RMA Action (without approval permissions); RMA action and approval permissions; RMA on Evaluations; SWO/HWO; Two Factor Authentication Required; Zenkraft - Standard User | D69: Salesforce | E69: Sales User | F69: Sales Rep | G69: Adam Walter | H69: Ultrasound Sales Specialist, Transducers | I69: Probo Medical, Inc. | J69: =COUNTIF('Direct Permission Sets'!$B$2:$B$7222,A69)
A70: bpaulsen@tgh.org | B70: Brenda Paulsen | D70: Customer Community Plus | E70: Tampa General Community Portal | F70: DCarr Customer Person Account | H70: Senior Director of Sterile Processing | I70: Tampa General Hospital | J70: =COUNTIF('Direct Permission Sets'!$B$2:$B$7222,A70)
A71: brendan.malone@probomedical.co.uk | B71: Brendan Malone | C71: Field Service Mobile License; Field Service Resource License; Field Service Resource Permissions; Flow User; Lead Access - FSL Tech (Can Create Leads); Product Analytics and Asset Permissions | D71: Salesforce | E71: Engineer - UK | G71: Adam Ward | H71: Senior Engineer | I71: Probo Medical Ltd | J71: =COUNTIF('Direct Permission Sets'!$B$2:$B$7222,A71)
A72: bwebb@probomedical.com | B72: Brenner Webb | C72: Add Asset Page; Add Product Page; All Record Types; All RMA Fields; Asset2- Review Status; Create new assets; Create Products; Creating New Products; Creating Price Books; Edit Product and Non-Serialized Qty in Stock; Edit Product Status; Edit Ratings Object; Edit Ratings/Notes on Asset Page; Functional Rating for Parts; Move Location Enabled; PandaDoc Access; Pandadoc Object Permissions; Part Tests and Repairs; Parts Operations; Parts Product Name Field; Parts Record Type; Parts Sales Record Type; Print Shipping Checklist Button; Product Repair Access; Shipping Team; Shipping/Receiving; SWO/HWO; Zenkraft - Standard User | D72: Salesforce | E72: QC Manager | H72: Lead Board Repair Engineer | I72: Probo Medical | J72: =COUNTIF('Direct Permission Sets'!$B$2:$B$7222,A72)
A73: blyman@probomedical.com | B73: Brent Lyman | C73: Access to harvest work orders; Add Asset Page; Add Product Page; All RMA Fields; Asset2- Review Status; Create Products; Creating New Products; Edit Ratings/Notes on Asset Page; Full access to equipment; Full access to work orders; Pandadoc Object Permissions; Part Tests and Repairs; Parts Operations; Parts Product Name Field; Parts Record Type; Parts Sales Record Type; Shipping Team; Shipping/Receiving; Zenkraft - Standard User | D73: Salesforce | E73: QC Manager | F73: Ops Tech | H73: Medical Imaging Repair Technician 1 | I73: Probo Medical LLC | J73: =COUNTIF('Direct Permission Sets'!$B$2:$B$7222,A73)
A74: bflieth@probomedical.com | B74: Brian Flieth | C74: Access to Account Quality fields; Add Product Page; All Record Types; All RMA Fields; Change Record Type RMA; Change RMA action; Create external repairs; Create Warranty Ops; Create Work Orders; Edit Public Reports; Edit Ratings Object; Edit Ratings/Notes on Asset Page; Edit Serial# on Assets; Full access to CAPAs and complaints; Full access to equipment; Full access to work orders; Functional Rating for Parts; Loaner Assets Object; Loaner Object; Non-Conforming Record Access; Pandadoc Object Permissions; Part Tests and Repairs; Parts Operations; Product Repair Access; Product Test; Product Test Edit; Quality Team Permission Set; Refurb Test & Refurb Part Request Permissions; Repairable Fields; Return from Sale RMA; RMA Action (without approval permissions); RMA on Evaluations; SWO/HWO; Two Factor Authentication Required; View Customer Satisfaction Surveys | D74: Salesforce | E74: Sales User | G74: Naomi Warmack | H74: Regulatory, EHS & Insurance Manager | I74: Probo Medical, Inc. | J74: =COUNTIF('Direct Permission Sets'!$B$2:$B$7222,A74)
A75: bgill@probomedical.com | B75: Brian Gill | C75: Access Drag-and-Drop Content Builder; Access to all price fields and product notes on Product Page; Access to purchasing fields but not creating opps; Account Engagement Connector User; Account Engagement Integration User; Account Engagement Package; Add Product Page; All Record Types; B2B Marketing Automation App; Branded Tracking; Change Account Owner; Create new assets; Creating New Products; Custom List Views; Deleting/Merging Accounts; e2a Email User; Edit Product and Non-Serialized Qty in Stock; Executive Power; Export Reports; Full access to equipment; Inventory Life; Loaner Assets Object; Loaner Object; Manage Assets; Marketing - Lead Assignment; Purchasing Fields; Record Types- Harrisburg Sales; Reports and Dashboards; Sales and Return Opps; Scan to Salesforce; Scan to Salesforce Admin; Shipping/Receiving; SWO/HWO; Systems Test; Total Cost of Assets; Trisonics User; Two Factor Authentication Required; Use Pardot Content Experience; View Customer Satisfaction Surveys; View FSR Attached Field; View Only Access to Evaluations | D75: Salesforce | E75: System Administrator Custom | F75: Sales Manager | I75: Probo Medical, Inc. | J75: =COUNTIF('Direct Permission Sets'!$B$2:$B$7222,A75)
A76: bkeith@probomedical.com | B76: Brian Keith | C76: Add Asset Page; Add Product Page; PandaDoc Access; Pandadoc Object Permissions | D76: Salesforce | E76: Sales Manager | F76: Sales Manager | H76: EVP of Sales, North America | I76: Probo Medical, Inc. | J76: =COUNTIF('Direct Permission Sets'!$B$2:$B$7222,A76)
A77: bwashington@probomedical.com | B77: Brittiney Washington | D77: Salesforce | E77: Accounting + Sales | G77: Lori Callahan | H77: Senior Accounts Payable Specialist | I77: Probo Medical | J77: =COUNTIF('Direct Permission Sets'!$B$2:$B$7222,A77)
A78: bking@probomedical.com | B78: Brittney King | C78: "Super User"; Access to purchasing fields but not creating opps; Add Asset Page; Add Product Page; All Account Fields; Change Account Owner; Create Purchasing Opps; Deleting/Merging Accounts; Edit Account Supervisor Field ONLY; Executive Power; Full access to evaluations; Loaner Assets Object; Loaner Object; PandaDoc Access; Pandadoc Object Permissions; Product Test Page Tab Visibility; Purchasing Fields; Sales Opp; Sales Opportunity Access; Ship to Account Opp; Shipping Account Number - Opps; Trisonics User; UK Admin Permission Set; Uncheck reserve box; Work Order Line Items; Work Order Shipping - Sales Ops; Zenkraft - Full Access | D78: Salesforce | E78: Sales Manager | H78: CS | I78: Probo Medical, Inc | J78: =COUNTIF('Direct Permission Sets'!$B$2:$B$7222,A78)
A79: bhaney@probomedical.com | B79: Brock Haney | C79: Field Service Mobile License; Field Service Resource License; Field Service Resource Permissions; Flow User; FSL Create Lead Perms; FSR Attached; Lead Access - FSL Tech (Can Create Leads); US FSL V1 Perm | D79: Salesforce | E79: FSL US | G79: Brad Lawson | H79: Senior Territory Manager | J79: =COUNTIF('Direct Permission Sets'!$B$2:$B$7222,A79)
A80: bruce.stacey@probomedical.co.uk | B80: Bruce Stacey | C80: Add Product Page; Asset Read and View ALL; Create Item Receipts; Field Service Mobile License; Field Service Resource License; Field Service Resource Permissions; Flow User; Lead Access - FSL Tech (Can Create Leads); PandaDoc Access; Pandadoc Object Permissions; Product Analytics and Asset Permissions; Warehouse FSL Visibility Permission Set | D80: Salesforce | E80: Commercial Manager - UK | F80: Engineer - UK | G80: Darren Stokes | H80: Transport Manager | I80: Probo Medical Ltd. | J80: =COUNTIF('Direct Permission Sets'!$B$2:$B$7222,A80)
A81: ceckholdt@probomedical.com | B81: Caleb Eckholdt | C81: Access to accounting info; Access to all price fields and product notes on Product Page; Access to harvest work orders; Access to purchasing fields but not creating opps; Add Asset Page; Add Product Page; All Record Types; AP Page - Cost; Asset Cost; Chargent Payment Console; Chargent Payment Request; Chargent Terminal Unlinked Payments; Chargent Terminal User; Chargent User (Base); Chargent User (Orders); Create Work Orders; Credit Memo- View Access; Edit Record Type on Asset; Edit sales price field on asset page; Full access to work orders; Handle Assets; Invoice Permissions; IR PR PO Bill Permissions; Manage Assets; Manage Intacct Synced Records; Override to Vet Deal; Pandadoc Object Permissions; Physical Location on Invoice Object; Purchasing Fields; RMA on Evaluations; Sales Opp; Sales Opportunity Access; Service Contract - Start and End Date Only; Service Contract Management; Shipping Cost; Shipping/Receiving; SWO/HWO; Total Cost of Assets; Trisonics User; View Only Access to Evaluations; Work Order Line Items; Work Order Shipping - Sales Ops | D81: Salesforce | E81: Accounting + Sales | G81: Zachary Hook | H81: Staff Accountant | I81: Probo Medical | J81: =COUNTIF('Direct Permission Sets'!$B$2:$B$7222,A81)
A82: callum.smith@probomedical.co.uk | B82: Callum Smith | C82: Field Service Mobile License; Field Service Resource License; Field Service Resource Permissions; Flow User; Lead Access - FSL Tech (Can Create Leads); Product Analytics and Asset Permissions | D82: Salesforce | E82: Engineer - UK | G82: Adam Ward | H82: Field Service Engineer | J82: =COUNTIF('Direct Permission Sets'!$B$2:$B$7222,A82)
A83: cjohns1@probomedical.com | B83: Cameron Johns | C83: Field Service Mobile License; Field Service Resource License; Field Service Resource Permissions; Flow User; FSL Create Lead Perms; FSR Attached; Lead Access - FSL Tech (Can Create Leads); US FSL V1 Perm | D83: Salesforce | E83: FSL US | J83: =COUNTIF('Direct Permission Sets'!$B$2:$B$7222,A83)
A84: cjohns@probomedical.com | B84: Cameron Johns | D84: Customer Community Plus | E84: FSE Portal | F84: Probo Medical - Portal Customer User | H84: FSE | J84: =COUNTIF('Direct Permission Sets'!$B$2:$B$7222,A84)
A85: cward@probomedical.com | B85: Cameron Ward | C85: Access to probe repair opps; Add Asset Page; Add Product Page; Create Work Orders; Edit Opportunities; Lead Owner Change; Marketing - Lead Assignment; PandaDoc Access; Pandadoc Object Permissions; Sales Opp; Sales Opportunity Access; Zenkraft - Full Access; ZoomInfo User | D85: Salesforce | E85: Sales User | F85: Sales Rep | G85: April Lebo | H85: Lead Gen Rep | I85: Probo Medical | J85: =COUNTIF('Direct Permission Sets'!$B$2:$B$7222,A85)
A86: camille.bailly@probomedical.fr | B86: Camille Bailly | C86: Modify All - Opportunities; Pandadoc Object Permissions; Product Analytics and Asset Permissions; Product Test; Product Test Edit; Project Edits - Full Access | D86: Salesforce | E86: Commercial Sales - UK | F86: Manager - UK | G86: Eric Floch | H86: Project Manager | I86: Probo Medical SAS | J86: =COUNTIF('Direct Permission Sets'!$B$2:$B$7222,A86)
A87: cneto@probomedical.com | B87: Candido Neto | C87: Add Product Page; All Record Types; Field Service Mobile License; Field Service Resource License; Field Service Resource Permissions; FieldServiceMobileStandardPermSetUS; Flow User; FSL Create Lead Perms; FSR Attached; Lead Access - FSL Tech (Can Create Leads); Loaner Assets Object; Loaner Object; Pandadoc Object Permissions; Scan to Salesforce; SWO/HWO; US FSL V1 Perm | D87: Salesforce | E87: Sales Manager | G87: Hobie Sears | H87: Engineer | J87: =COUNTIF('Direct Permission Sets'!$B$2:$B$7222,A87)
A88: cdefelice@probomedical.com | B88: Carli deFelice-Mitchell | C88: Add Asset Page; Add Product Page; Cold Storage - Invoicing; Cold Storage - Warehouse Reps; Location Unlocked; Move Location Enabled; PandaDoc Access; Pandadoc Object Permissions; Training Class/Class Attendance Access | D88: Salesforce | E88: Sales Manager | I88: AlphaSource Group | J88: =COUNTIF('Direct Permission Sets'!$B$2:$B$7222,A88)
A89: cmontalvo@probomedical.com | B89: Carmen Montalvo | C89: Able to Edit Sales Tax; Access to accounting info; Add Product Page; All Record Types; AP Page - Cost; Change Invoice Number on Opp; Change Opp Once Synced; Chargent Payment Console; Chargent Payment Request; Chargent User (Base); Chargent User (Orders); Cold Storage - Invoicing; Create Warranty Ops; Credit Memo Permission Set; Credit Memo- View Access; D&B; Inventory Life; Invoice Create; Invoice Permissions; Loaner Assets Object; Loaner Object; Manage Billing Address on Intacct Synced Account; Manage Intacct Synced Records; Manage Payment Terms, Credit Limit on Intacct Synced Account; Pandadoc Object Permissions; Parts Sales Record Type; Purchasing Fields; Reports and Dashboards; Run Convert Proforma; Sales Opp; Service Contract - Start and End Date Only; Shipping Cost; SWO/HWO; Total Cost of Assets; View FSR Attached Field | D89: Salesforce | E89: Accounting + Sales | F89: Sales Rep | I89: Probo Medical, Inc. | J89: =COUNTIF('Direct Permission Sets'!$B$2:$B$7222,A89)
A90: caroline.clinton@probomedical.co.uk | B90: Caroline Clinton | C90: Add Product Page; Create Products; Field Service Dispatcher License; Field Service Dispatcher Permissions; Flow User; PandaDoc Access; Pandadoc Object Permissions; Product Analytics and Asset Permissions; Sales Opp; Sales Opportunity Access | D90: Salesforce | E90: Commercial Sales - UK | F90: Coordinator - UK | G90: Tom Meredith | H90: Engineering Support Manager | I90: Probo Medical Ltd. | J90: =COUNTIF('Direct Permission Sets'!$B$2:$B$7222,A90)
A91: caroline.keeling@probomedical.co.uk | B91: Caroline Keeling | C91: Field Service Dispatcher License; Field Service Dispatcher Permissions; Flow User; Pandadoc Object Permissions; Product Analytics and Asset Permissions | D91: Salesforce | E91: Ops Coordinator - UK | F91: Coordinator - UK | G91: Tom Meredith | H91: Service Coordinator | I91: Probo Medical, Ltd. | J91: =COUNTIF('Direct Permission Sets'!$B$2:$B$7222,A91)
A92: catholic_health_initiatives@ultrasoundrepair.force.com | B92: Catholic Health Initiatives Site Guest User | D92: Guest User License | E92: Catholic Health Initiatives Profile | J92: =COUNTIF('Direct Permission Sets'!$B$2:$B$7222,A92)
A93: cflinchum@probomedical.com | B93: Cathy Flinchum | C93: Add Product Page; All Record Types; Asset and Product Analytics Modify All; Edit Review Status Object; Loaner Assets Object; Loaner Object; Modify All - Assets; SWO/HWO; Two Factor Authentication Required; Unable to further improve - functional and cosmetic | D93: Salesforce | E93: Repair Tech | I93: Probo Medical, Inc. | J93: =COUNTIF('Direct Permission Sets'!$B$2:$B$7222,A93)
A94: cdornquast@probomedical.com | B94: Chad Dornquast | C94: Add Asset Page; Add Product Page; PandaDoc Access; Pandadoc Object Permissions | D94: Salesforce | E94: Sales Manager | H94: Trainer / Technical Support Specialist | I94: Probo Medical, Inc. | J94: =COUNTIF('Direct Permission Sets'!$B$2:$B$7222,A94)
A95: charlie@davismedical.com | B95: Charlie Abel | C95: Access to Product & Repair Pricing; Access to purchasing fields but not creating opps; Add Asset Page; Add Product Page; All RMA Fields; Asset and Product Analytics Modify All; Asset Cost; Asset2- Review Status; Certain Asset Fields; Create new assets; Create Products; Create Purchasing Opps; Edit Ratings/Notes on Asset Page; Edit Record Type on Asset; Edit Serial# on Assets; IR PR PO Bill Permissions; Pandadoc Object Permissions; Purchasing Fields; Sales and Return Opps; Sales Opp; Sales Opportunity Access; Switch to Lightning; Work Order Line Items | D95: Salesforce | E95: Sales with Purchasing | F95: Sales Manager | H95: Manager, Cardiac Solutions | I95: Probo Medical - formerly Davis Medical Electronics | J95: =COUNTIF('Direct Permission Sets'!$B$2:$B$7222,A95)
A96: charlotte.lonsdale@probomedical.co.uk | B96: Charlotte Lonsdale | C96: Add Product Page; Create Item Receipts; Pandadoc Object Permissions; Product Analytics and Asset Permissions | D96: Salesforce | E96: Commercial Manager - UK | F96: Mechanical Services - UK | G96: Darren Stokes | H96: Shipping & Logistics Coordinator | I96: Probo Medical Ltd. | J96: =COUNTIF('Direct Permission Sets'!$B$2:$B$7222,A96)
A97: chatty.00du0000000lakomak.vzfdsrltr0oe@chatter.salesforce.com | B97: Chatter Expert | D97: Chatter Free | E97: Chatter Free User | J97: =COUNTIF('Direct Permission Sets'!$B$2:$B$7222,A97)
A98: chris.dall-smith@probomedical.co.uk | B98: Chris Dall-Smith | C98: Calibration Access; Creating New Products; Edit cost fields; Edit Product Status; Field Service Dispatcher License; Field Service Dispatcher Permissions; Field Service Mobile License; Field Service Resource License; Field Service Resource Permissions; Flow User; Pandadoc Object Permissions; Product Analytics and Asset Permissions; SWO/HWO | D98: Salesforce | E98: Commercial Sales - UK | F98: Manager - UK | G98: Tom Meredith | J98: =COUNTIF('Direct Permission Sets'!$B$2:$B$7222,A98)
A99: cknowles@probomedical.com | B99: Chris Knowles | C99: Able to Edit Sales Tax; Access to accounting info; Add Asset Page; Add Product Page; Change Invoice Number on Opp; Change Opp Once Synced; Chargent Admin (Base); Chargent Admin (Orders); Chargent Create Orders; Chargent Create Payment Methods; Chargent Delete Payment Methods; Chargent Edit Orders; Chargent Edit Payment Methods; Chargent Payment Console; Chargent Payment Methods Use Pay Forms; Chargent Payment Request; Chargent Read Gateways; Chargent Terminal Admin; Chargent Terminal Unlinked Payments; Chargent Terminal User; Chargent User (Base); Chargent User (Orders); Chargent Waive Surcharge; Cold Storage - Invoicing; Credit Memo Permission Set; Credit Memo- View Access; Disaster Recovery Projects - Access; Invoice Create; Invoice Permissions; IR PR PO Bill Permissions; Manage Billing Address on Intacct Synced Account; Manage Intacct Synced Records; Manage Payment Terms, Credit Limit on Intacct Synced Account; PandaDoc Access; Pandadoc Object Permissions | D99: Salesforce | E99: Accounting + Sales | G99: Jason Ribero | H99: Director of Marketing & Billing Support | I99: Probo Medical | J99: =COUNTIF('Direct Permission Sets'!$B$2:$B$7222,A99)
A100: csanchez@probomedical.com | B100: Chris Sanchez | C100: Add Product Page; All Record Types; Asset and Product Analytics Modify All; Create Products; Full access to evaluations; Loaner Assets Object; Loaner Object; Modify All - Assets; Print Shipping Checklist Button; Product Test Edit; Product Test Settings Access on Product Page; Shipping Account Number - Opps; Shipping Cost; Shipping Team; Shipping/Receiving; SWO/HWO; Two Factor Authentication Required; Work Order Shipping - Sales Ops; Zenkraft - Full Access; Zenkraft - Read Only; Zenkraft - Standard User | D100: Salesforce | E100: QC/Inspection | I100: Probo Medical, Inc. | J100: =COUNTIF('Direct Permission Sets'!$B$2:$B$7222,A100)
...

Sheet Direct Permission Sets
A1: User Name | B1: Username | C1: Email | D1: User Type | E1: Profile | F1: Permission Set Label | G1: Permission Set API Name | H1: Permission Set Type | I1: Modify All Data | J1: View All Data | K1: Assignment Source | L1: User Id | M1: Permission Set Id
A2: Aaliyah Reid | B2: areid@probomedical.com | C2: areid@probomedical.com | D2: Standard | E2: Sales Manager | F2: "Super User" | G2: Super_User | H2: Regular | I2: TRUE | J2: TRUE | K2: Direct Permission Set | L2: 005Ro00000G5TJVIA3 | M2: 0PS4O000000vMZBWA2
A3: Aaliyah Reid | B3: areid@probomedical.com | C3: areid@probomedical.com | D3: Standard | E3: Sales Manager | F3: Access to purchasing fields but not creating opps | G3: Access_to_purchasing_fields_but_not_creating_opps | H3: Regular | I3: FALSE | J3: FALSE | K3: Direct Permission Set | L3: 005Ro00000G5TJVIA3 | M3: 0PS0B000000b6U4WAI
A4: Aaliyah Reid | B4: areid@probomedical.com | C4: areid@probomedical.com | D4: Standard | E4: Sales Manager | F4: Add Asset Page | G4: Add_Asset_Page | H4: Regular | I4: FALSE | J4: FALSE | K4: Direct Permission Set | L4: 005Ro00000G5TJVIA3 | M4: 0PS4O000000zpzaWAA
A5: Aaliyah Reid | B5: areid@probomedical.com | C5: areid@probomedical.com | D5: Standard | E5: Sales Manager | F5: Add Product Page | G5: Add_Product_Page | H5: Regular | I5: FALSE | J5: FALSE | K5: Direct Permission Set | L5: 005Ro00000G5TJVIA3 | M5: 0PS4O0000009SmrWAE
A6: Aaliyah Reid | B6: areid@probomedical.com | C6: areid@probomedical.com | D6: Standard | E6: Sales Manager | F6: All Account Fields | G6: All_Account_Fields | H6: Regular | I6: FALSE | J6: FALSE | K6: Direct Permission Set | L6: 005Ro00000G5TJVIA3 | M6: 0PS5b000001V1tdGAC
A7: Aaliyah Reid | B7: areid@probomedical.com | C7: areid@probomedical.com | D7: Standard | E7: Sales Manager | F7: Change Account Owner | G7: Change_Account_Owner | H7: Regular | I7: FALSE | J7: FALSE | K7: Direct Permission Set | L7: 005Ro00000G5TJVIA3 | M7: 0PS4O000000OaONWA0
A8: Aaliyah Reid | B8: areid@probomedical.com | C8: areid@probomedical.com | D8: Standard | E8: Sales Manager | F8: Create Item Receipts | G8: Create_Item_Receipts | H8: Regular | I8: FALSE | J8: FALSE | K8: Direct Permission Set | L8: 005Ro00000G5TJVIA3 | M8: 0PS5b000000HmZ0GAK
A9: Aaliyah Reid | B9: areid@probomedical.com | C9: areid@probomedical.com | D9: Standard | E9: Sales Manager | F9: Create new assets | G9: Create_new_assets | H9: Regular | I9: FALSE | J9: FALSE | K9: Direct Permission Set | L9: 005Ro00000G5TJVIA3 | M9: 0PS0B000000b6NDWAY
A10: Aaliyah Reid | B10: areid@probomedical.com | C10: areid@probomedical.com | D10: Standard | E10: Sales Manager | F10: Create Purchasing Opps | G10: Create_Purchasing_Opps | H10: Regular | I10: FALSE | J10: FALSE | K10: Direct Permission Set | L10: 005Ro00000G5TJVIA3 | M10: 0PS4O000000WtjbWAC
A11: Aaliyah Reid | B11: areid@probomedical.com | C11: areid@probomedical.com | D11: Standard | E11: Sales Manager | F11: Creating Price Books | G11: Creating_Price_Books | H11: Regular | I11: FALSE | J11: FALSE | K11: Direct Permission Set | L11: 005Ro00000G5TJVIA3 | M11: 0PS5b000000DkfJGAS
A12: Aaliyah Reid | B12: areid@probomedical.com | C12: areid@probomedical.com | D12: Standard | E12: Sales Manager | F12: Edit Loaner Fields | G12: Edit_Loaner_Fields | H12: Regular | I12: FALSE | J12: FALSE | K12: Direct Permission Set | L12: 005Ro00000G5TJVIA3 | M12: 0PS4O000000zq3SWAQ
A13: Aaliyah Reid | B13: areid@probomedical.com | C13: areid@probomedical.com | D13: Standard | E13: Sales Manager | F13: Endoscopy Test/Repair Permission Set | G13: Endoscopy_Permission_Set | H13: Regular | I13: FALSE | J13: FALSE | K13: Direct Permission Set | L13: 005Ro00000G5TJVIA3 | M13: 0PSRo0000002N5NOAU
... A5728: Phoebe Ding | B5728: pding@probomedical.com | C5728: pding@probomedical.com | D5728: Standard | E5728: Accounting + Sales | F5728: Pandadoc Object Permissions | G5728: Pandadoc_Object_Permissions | H5728: Regular | I5728: FALSE | J5728: FALSE | K5728: Direct Permission Set | L5728: 005Ro000004A0CXIA0 | M5728: 0PS5b000001QEQAGA4
A5729: Platform Integration User | B5729: cloud@00du0000000lakomak | C5729: noreply@salesforce.com | D5729: CloudIntegrationUser | F5729: Chatbot | G5729: sfdc_chatbot | H5729: Session | I5729: FALSE | J5729: FALSE | K5729: Direct Permission Set | L5729: 0054O0000095zVrQAI | M5729: 0PSRo000000D0obOAC
A5730: Platform Integration User | B5730: cloud@00du0000000lakomak | C5730: noreply@salesforce.com | D5730: CloudIntegrationUser | F5730: Constraint Rules Engine Licenseless permission set | G5730: sfdc_nc_constraints_engine_deploy | H5730: Session | I5730: FALSE | J5730: FALSE | K5730: Direct Permission Set | L5730: 0054O0000095zVrQAI | M5730: 0PSRo000000C1oMOAS
A5731: Platform Integration User | B5731: cloud@00du0000000lakomak | C5731: noreply@salesforce.com | D5731: CloudIntegrationUser | F5731: Field Service Integration | G5731: sfdc_fieldservice | H5731: Session | I5731: FALSE | J5731: FALSE | K5731: Direct Permission Set | L5731: 0054O0000095zVrQAI | M5731: 0PSRo0000003vszOAA
A5732: Platform Integration User | B5732: cloud@00du0000000lakomak | C5732: noreply@salesforce.com | D5732: CloudIntegrationUser | F5732: SCRT2 Integration User | G5732: sfdc_scrt2 | H5732: Session | I5732: FALSE | J5732: FALSE | K5732: Direct Permission Set | L5732: 0054O0000095zVrQAI | M5732: 0PSRo0000008PHgOAM
A5733: Platform Integration User | B5733: cloud@00du0000000lakomak | C5733: noreply@salesforce.com | D5733: CloudIntegrationUser | F5733: sfdc.activityplatform | G5733: sfdc_activityplatform | H5733: Session | I5733: FALSE | J5733: FALSE | K5733: Direct Permission Set | L5733: 0054O0000095zVrQAI | M5733: 0PSRo000000GIYrOAO
A5734: Platform Integration User | B5734: cloud@00du0000000lakomak | C5734: noreply@salesforce.com | D5734: CloudIntegrationUser | F5734: sfdc.aiplanner.service.permset | G5734: sfdc_aiplanner_service_permset | H5734: Session | I5734: FALSE | J5734: FALSE | K5734: Direct Permission Set | L5734: 0054O0000095zVrQAI | M5734: 0PSRo000000D0mzOAC
A5735: Preston Allred | B5735: pallred@probomedical.com | C5735: pallred@probomedical.com | D5735: Standard | E5735: Shipping | F5735: Asset and Product Analytics Modify All | G5735: Asset_and_Product_Analytics_Modify_All | H5735: Regular | I5735: FALSE | J5735: FALSE | K5735: Direct Permission Set | L5735: 005Ro00000CBzR3IAL | M5735: 0PSRo000000FMcvOAG
A5736: Preston Allred | B5736: pallred@probomedical.com | C5736: pallred@probomedical.com | D5736: Standard | E5736: Shipping | F5736: Asset2- Review Status | G5736: Asset2_Review_Status | H5736: Regular | I5736: FALSE | J5736: FALSE | K5736: Direct Permission Set | L5736: 005Ro00000CBzR3IAL | M5736: 0PS4O000000zpzzWAA
A5737: Preston Allred | B5737: pallred@probomedical.com | C5737: pallred@probomedical.com | D5737: Standard | E5737: Shipping | F5737: Create and Edit Purchasing Returns | G5737: Create_and_Edit_Purchasing_Returns | H5737: Regular | I5737: FALSE | J5737: FALSE | K5737: Direct Permission Set | L5737: 005Ro00000CBzR3IAL | M5737: 0PSRo0000007CSfOAM
A5738: Preston Allred | B5738: pallred@probomedical.com | C5738: pallred@probomedical.com | D5738: Standard | E5738: Shipping | F5738: Field Service Dispatcher License | G5738: FSL_Dispatcher_License | H5738: Regular | I5738: FALSE | J5738: FALSE | K5738: Direct Permission Set | L5738: 005Ro00000CBzR3IAL | M5738: 0PSRo0000003wnSOAQ
A5739: Preston Allred | B5739: pallred@probomedical.com | C5739: pallred@probomedical.com | D5739: Standard | E5739: Shipping | F5739: Functional Rating for Parts | G5739: Functional_Rating_for_Parts | H5739: Regular | I5739: FALSE | J5739: FALSE | K5739: Direct Permission Set | L5739: 005Ro00000CBzR3IAL | M5739: 0PS4O000000Wta0WAC
A5740: Preston Allred | B5740: pallred@probomedical.com | C5740: pallred@probomedical.com | D5740: Standard | E5740: Shipping | F5740: Location Unlocked | G5740: Location_Unlocked | H5740: Regular | I5740: FALSE | J5740: FALSE | K5740: Direct Permission Set | L5740: 005Ro00000CBzR3IAL | M5740: 0PS4O000000WuOKWA0
A5741: Preston Allred | B5741: pallred@probomedical.com | C5741: pallred@probomedical.com | D5741: Standard | E5741: Shipping | F5741: Manage Assets | G5741: Manage_Assets | H5741: Regular | I5741: FALSE | J5741: FALSE | K5741: Direct Permission Set | L5741: 005Ro00000CBzR3IAL | M5741: 0PS0B000000zmzOWAQ
A5742: Preston Allred | B5742: pallred@probomedical.com | C5742: pallred@probomedical.com | D5742: Standard | E5742: Shipping | F5742: Print Shipping Checklist Button | G5742: Print_Shipping_Checklist_Button | H5742: Regular | I5742: FALSE | J5742: FALSE | K5742: Direct Permission Set | L5742: 005Ro00000CBzR3IAL | M5742: 0PS4O0000009Sf7WAE
A5743: Preston Allred | B5743: pallred@probomedical.com | C5743: pallred@probomedical.com | D5743: Standard | E5743: Shipping | F5743: Shipping Account Number - Opps | G5743: Shipping_Account_Number_Opps | H5743: Regular | I5743: FALSE | J5743: FALSE | K5743: Direct Permission Set | L5743: 005Ro00000CBzR3IAL | M5743: 0PS5b000000HiSwGAK
A5744: Preston Allred | B5744: pallred@probomedical.com | C5744: pallred@probomedical.com | D5744: Standard | E5744: Shipping | F5744: Shipping Cost | G5744: Shipping_Cost | H5744: Regular | I5744: FALSE | J5744: FALSE | K5744: Direct Permission Set | L5744: 005Ro00000CBzR3IAL | M5744: 0PS4O0000009WeiWAE
A5745: Preston Allred | B5745: pallred@probomedical.com | C5745: pallred@probomedical.com | D5745: Standard | E5745: Shipping | F5745: Shipping Team | G5745: Shipping_Team | H5745: Regular | I5745: FALSE | J5745: FALSE | K5745: Direct Permission Set | L5745: 005Ro00000CBzR3IAL | M5745: 0PS5b000000HiFEGA0
A5746: Preston Allred | B5746: pallred@probomedical.com | C5746: pallred@probomedical.com | D5746: Standard | E5746: Shipping | F5746: Shipping/Receiving | G5746: Shipping_Receiving | H5746: Regular | I5746: FALSE | J5746: FALSE | K5746: Direct Permission Set | L5746: 005Ro00000CBzR3IAL | M5746: 0PS0B000000b6NmWAI
... A7222: ZoomInfoAdmin | B7222: zoominfoadmin@probomedical.com | C7222: sdodd@probomedical.com | D7222: Standard | E7222: System Administrator Custom | F7222: Waive MFA | G7222: Waive_MFA | H7222: Regular | I7222: FALSE | J7222: FALSE | K7222: Direct Permission Set | L7222: 005Ro00000FaiLFIAZ | M7222: 0PSRo000000815NOAQ
